{
  "fileName": "hashing_discretizer_impl.h",
  "filePath": "twml/libtwml/include/twml/hashing_discretizer_impl.h",
  "url": "https://github.com/misbahsy/the-algorithm/twml/libtwml/include/twml/hashing_discretizer_impl.h",
  "summary": "The code above is a C++ header file that defines a function called `hashDiscretizerInfer`. This function takes in several parameters, including input and output tensors, as well as various integer values and a map. The purpose of this function is to perform a hash discretization operation on the input data and return the resulting keys and values in the output tensors.\n\nHash discretization is a technique used in machine learning to convert continuous data into discrete values. This is often done to reduce the dimensionality of the data and make it easier to work with. In this case, the input data is represented as a set of IDs and values, and the function uses a hash function to map each ID to a discrete value. The resulting keys and values are then stored in the output tensors.\n\nThe function takes in several parameters that control the behavior of the hash discretization operation. These include the number of bins to use, the values to use for each bin, and the number of bits to use for the output keys. The function also takes in a map that maps each ID to an index, which is used to look up the corresponding value in the input tensor.\n\nOverall, this function is an important part of the larger project, as it provides a key operation for converting continuous data into discrete values. This operation is likely used in various machine learning models and algorithms within the project. Here is an example of how this function might be used:\n\n```\n#include <twml/hashDiscretizer.h>\n\n// create input tensors\nTensor input_ids = ...;\nTensor input_vals = ...;\n\n// create output tensors\nTensor output_keys = ...;\nTensor output_vals = ...;\n\n// set up other parameters\nint n_bin = ...;\nTensor bin_vals = ...;\nint output_bits = ...;\nMap<int64_t, int64_t> ID_to_index = ...;\nint start_compute = ...;\nint end_compute = ...;\nint64_t options = ...;\n\n// call hashDiscretizerInfer function\ntwml::hashDiscretizerInfer(output_keys, output_vals, input_ids, input_vals, n_bin, bin_vals, output_bits, ID_to_index, start_compute, end_compute, options);\n```",
  "questions": "1. What is the purpose of this code?\n- This code defines a function called `hashDiscretizerInfer` within the `twml` namespace. The function takes in several input tensors and parameters, and outputs two tensors. It likely performs some sort of hashing and discretization operation.\n\n2. What are the input and output data types for the `hashDiscretizerInfer` function?\n- The input data types are `Tensor`, `int`, and `Map<int64_t, int64_t>`. The output data types are also `Tensor`. It is unclear what the specific data types of the tensors are, as they are defined in other files.\n\n3. What is the purpose of the `Map<int64_t, int64_t>` parameter in the `hashDiscretizerInfer` function?\n- The `Map<int64_t, int64_t>` parameter is likely used to map unique IDs to their corresponding indices. This mapping is likely used in the hashing and discretization process."
}